odoo/addons/l10n_be_cooperator_portal_national_number/README.rst
odoo/addons/l10n_be_cooperator_portal_national_number/__init__.py
odoo/addons/l10n_be_cooperator_portal_national_number/__manifest__.py
odoo/addons/l10n_be_cooperator_portal_national_number/controllers/__init__.py
odoo/addons/l10n_be_cooperator_portal_national_number/controllers/portal.py
odoo/addons/l10n_be_cooperator_portal_national_number/i18n/it.po
odoo/addons/l10n_be_cooperator_portal_national_number/i18n/l10n_be_cooperator_portal_national_number.pot
odoo/addons/l10n_be_cooperator_portal_national_number/models/__init__.py
odoo/addons/l10n_be_cooperator_portal_national_number/models/res_partner.py
odoo/addons/l10n_be_cooperator_portal_national_number/readme/CONTRIBUTORS.rst
odoo/addons/l10n_be_cooperator_portal_national_number/readme/DESCRIPTION.rst
odoo/addons/l10n_be_cooperator_portal_national_number/static/description/icon.png
odoo/addons/l10n_be_cooperator_portal_national_number/static/description/index.html
odoo/addons/l10n_be_cooperator_portal_national_number/views/portal_templates.xml
odoo_addon_l10n_be_cooperator_portal_national_number-16.0.1.0.0.5.dist-info/METADATA
odoo_addon_l10n_be_cooperator_portal_national_number-16.0.1.0.0.5.dist-info/WHEEL
odoo_addon_l10n_be_cooperator_portal_national_number-16.0.1.0.0.5.dist-info/top_level.txt
odoo_addon_l10n_be_cooperator_portal_national_number-16.0.1.0.0.5.dist-info/RECORD
