Metadata-Version: 2.1
Name: odoo-addon-l10n-be-cooperator-portal-national-number
Version: 16.0.1.0.0.5
Summary: Add the ability to change national number on the account portal.
Home-page: https://github.com/OCA/cooperative
Author: Coop IT Easy SC, Odoo Community Association (OCA)
Author-email: support@odoo-community.org
License: AGPL-3
Platform: UNKNOWN
Classifier: Programming Language :: Python
Classifier: Framework :: Odoo
Classifier: Framework :: Odoo :: 16.0
Classifier: License :: OSI Approved :: GNU Affero General Public License v3
Requires-Python: >=3.10
Requires-Dist: odoo-addon-cooperator-portal <16.1dev,>=16.0dev
Requires-Dist: odoo-addon-l10n-be-cooperator-national-number <16.1dev,>=16.0dev
Requires-Dist: odoo <16.1dev,>=16.0a
